gastimeter/__init__.py
gastimeter/analyzer.py
gastimeter/configator.py
gastimeter/error.py
gastimeter/imagegrabber.py
gastimeter/preprocessor.py
gastimeter/responseparser.py
gastimeter/cli/__init__.py
gastimeter/cli/cli.py
gastimeter-0.2.4.dist-info/METADATA
gastimeter-0.2.4.dist-info/WHEEL
gastimeter-0.2.4.dist-info/entry_points.txt
gastimeter-0.2.4.dist-info/top_level.txt
gastimeter-0.2.4.dist-info/RECORD
