Metadata-Version: 2.4
Name: gastimeter
Version: 0.2.4
Summary: Extract text from an image using Azure Cognitive Services.
Author-email: Georg Kunz <der.schorsch@gmail.com>
Project-URL: Homepage, https://github.com/gkunz/gastimeter
Classifier: Development Status :: 4 - Beta
Classifier: Intended Audience :: End Users/Desktop
Classifier: License :: OSI Approved :: MIT License
Classifier: Programming Language :: Python :: 3
Classifier: Programming Language :: Python :: 3.8
Classifier: Programming Language :: Python :: 3.9
Requires-Python: >=3.8
Requires-Dist: opencv-python==4.12.0.88
Requires-Dist: numpy<3.0.0
